{
  "adrProfiles": [
    {
      "rxnormCode": "<LOOKUP_REQUIRED>",
      "drugName": "diuretic",
      "drugClass": "diuretic",
      "reaction": "acute kidney injury",
      "reactionSnomed": null,
      "mechanism": "kidney hypoperfusion",
      "symptom": "hypotension",
      "onsetWindow": "acute",
      "onsetCategory": "ACUTE",
      "frequency": null,
      "severity": "HIGH",
      "riskFactors": [
        "low eGFR",
        "concurrent medications",
        "volume depletion",
        "tenuous volume status"
      ],
      "contextualModifiers": [
        {
          "modifierType": "POPULATION",
          "modifierValue": "patients with high risk of acute kidney injury due to low eGFR",
          "effect": "increases risk",
          "effectMagnitude": null,
          "labParameter": null,
          "labOperator": null,
          "labThreshold": null,
          "labUnit": null,
          "concomitantDrug": null,
          "concomitantRxnorm": null,
          "contextModifierRule": null,
          "completenessGrade": "PARTIAL"
        },
        {
          "modifierType": "CONCOMITANT_DRUG",
          "modifierValue": "SGLT2 inhibitors",
          "effect": "increases risk of volume depletion and AKI",
          "effectMagnitude": null,
          "labParameter": null,
          "labOperator": null,
          "labThreshold": null,
          "labUnit": null,
          "concomitantDrug": "SGLT2 inhibitors",
          "concomitantRxnorm": "<LOOKUP_REQUIRED>",
          "contextModifierRule": null,
          "completenessGrade": "FULL"
        }
      ],
      "completenessGrade": "FULL",
      "sourceSnippet": "Diuretics can precipitate acute kidney injury (AKI) and electrolyte abnormalities...concern for volume depletion and AKI, particularly among patients treated concurrently with diuretics",
      "governance": {
        "sourceAuthority": "KDIGO",
        "sourceDocument": "KDIGO 2022 Diabetes in CKD",
        "sourceSection": "Practice Point 1.3.3, 1.3.4",
        "evidenceLevel": "",
        "effectiveDate": "2022-11-01",
        "guidelineDoi": "10.1016/j.kint.2022.06.008"
      }
    },
    {
      "rxnormCode": "<LOOKUP_REQUIRED>",
      "drugName": "diuretic",
      "drugClass": "diuretic",
      "reaction": "electrolyte abnormalities",
      "reactionSnomed": null,
      "mechanism": "diminished hypokalemic response with low eGFR",
      "symptom": null,
      "onsetWindow": null,
      "onsetCategory": null,
      "frequency": null,
      "severity": "MODERATE",
      "riskFactors": [
        "low eGFR"
      ],
      "contextualModifiers": [
        {
          "modifierType": "LAB_VALUE",
          "modifierValue": "low eGFR",
          "effect": "diminishes hypokalemic response",
          "effectMagnitude": null,
          "labParameter": "eGFR",
          "labOperator": "<",
          "labThreshold": 30.0,
          "labUnit": "mL/min/1.73m\u00b2",
          "concomitantDrug": null,
          "concomitantRxnorm": null,
          "contextModifierRule": null,
          "completenessGrade": "FULL"
        }
      ],
      "completenessGrade": "PARTIAL",
      "sourceSnippet": "Diuretics can precipitate acute kidney injury (AKI) and electrolyte abnormalities, and the hypokalemic response to diuretics is diminished with low eGFR",
      "governance": {
        "sourceAuthority": "KDIGO",
        "sourceDocument": "KDIGO 2022 Diabetes in CKD",
        "sourceSection": "Practice Point 1.3.3",
        "evidenceLevel": "",
        "effectiveDate": "2022-11-01",
        "guidelineDoi": "10.1016/j.kint.2022.06.008"
      }
    },
    {
      "rxnormCode": "<LOOKUP_REQUIRED>",
      "drugName": "thiazide diuretic",
      "drugClass": "thiazide diuretic",
      "reaction": "hyperglycemia",
      "reactionSnomed": null,
      "mechanism": null,
      "symptom": null,
      "onsetWindow": null,
      "onsetCategory": null,
      "frequency": null,
      "severity": "MODERATE",
      "riskFactors": [],
      "contextualModifiers": [],
      "completenessGrade": "STUB",
      "sourceSnippet": "Effects of low-dose thiazide diuretics on fasting plasma glucose and serum potassium",
      "governance": {
        "sourceAuthority": "KDIGO",
        "sourceDocument": "KDIGO 2022 Diabetes in CKD",
        "sourceSection": "References",
        "evidenceLevel": "",
        "effectiveDate": "2022-11-01",
        "guidelineDoi": "10.1016/j.kint.2022.06.008"
      }
    },
    {
      "rxnormCode": "<LOOKUP_REQUIRED>",
      "drugName": "potassium-sparing diuretics",
      "drugClass": "potassium-sparing diuretic",
      "reaction": "hyperkalemia",
      "reactionSnomed": null,
      "mechanism": "potassium retention",
      "symptom": null,
      "onsetWindow": null,
      "onsetCategory": null,
      "frequency": null,
      "severity": "MODERATE",
      "riskFactors": [
        "advanced CKD",
        "salt substitutes containing potassium chloride"
      ],
      "contextualModifiers": [
        {
          "modifierType": "COMORBIDITY",
          "modifierValue": "advanced CKD",
          "effect": "increases risk of hyperkalemia",
          "effectMagnitude": null,
          "labParameter": null,
          "labOperator": null,
          "labThreshold": null,
          "labUnit": null,
          "concomitantDrug": null,
          "concomitantRxnorm": null,
          "contextModifierRule": null,
          "completenessGrade": "PARTIAL"
        },
        {
          "modifierType": "CONCOMITANT_DRUG",
          "modifierValue": "salt substitutes containing potassium chloride",
          "effect": "may contribute to hyperkalemia",
          "effectMagnitude": null,
          "labParameter": null,
          "labOperator": null,
          "labThreshold": null,
          "labUnit": null,
          "concomitantDrug": "potassium chloride",
          "concomitantRxnorm": "<LOOKUP_REQUIRED>",
          "contextModifierRule": null,
          "completenessGrade": "FULL"
        }
      ],
      "completenessGrade": "PARTIAL",
      "sourceSnippet": "Salt substitutes containing potassium chloride should be used with caution in patients with advanced CKD or those taking potassium-sparing diuretics, as they may contribute to hyperkalemia",
      "governance": {
        "sourceAuthority": "KDIGO",
        "sourceDocument": "KDIGO 2022 Diabetes in CKD",
        "sourceSection": "Practice Point",
        "evidenceLevel": "",
        "effectiveDate": "2022-11-01",
        "guidelineDoi": "10.1016/j.kint.2022.06.008"
      }
    }
  ],
  "standaloneModifiers": [
    {
      "modifierType": "CONCOMITANT_DRUG",
      "modifierValue": "diuretic dose reduction with SGLT2i initiation",
      "effect": "reduces volume depletion risk",
      "effectMagnitude": null,
      "labParameter": null,
      "labOperator": null,
      "labThreshold": null,
      "labUnit": null,
      "concomitantDrug": "SGLT2 inhibitors",
      "concomitantRxnorm": "<LOOKUP_REQUIRED>",
      "contextModifierRule": null,
      "completenessGrade": "FULL"
    },
    {
      "modifierType": "TEMPORAL",
      "modifierValue": "2-4 weeks after starting ACEi or ARB",
      "effect": "monitor serum creatinine and potassium",
      "effectMagnitude": null,
      "labParameter": null,
      "labOperator": null,
      "labThreshold": null,
      "labUnit": null,
      "concomitantDrug": null,
      "concomitantRxnorm": null,
      "contextModifierRule": null,
      "completenessGrade": "PARTIAL"
    },
    {
      "modifierType": "LAB_VALUE",
      "modifierValue": "greater than 30% increase in creatinine",
      "effect": "reassess concomitant medications including diuretics",
      "effectMagnitude": null,
      "labParameter": "creatinine",
      "labOperator": ">",
      "labThreshold": 30.0,
      "labUnit": "% increase",
      "concomitantDrug": null,
      "concomitantRxnorm": null,
      "contextModifierRule": null,
      "completenessGrade": "FULL"
    }
  ],
  "extractionDate": "2026-03-03",
  "extractorVersion": "v4.0.0-facts",
  "sourceGuideline": "KDIGO 2022 Diabetes in CKD",
  "totalAdrProfiles": 4,
  "totalContextualModifiers": 8,
  "completenessSummary": {
    "FULL": 1,
    "PARTIAL": 2,
    "STUB": 1
  }
}