{
  "drugs": [
    {
      "rxnormCode": "<LOOKUP_REQUIRED>",
      "drugName": "spironolactone",
      "drugClass": "mineralocorticoid receptor antagonist",
      "renalAdjustments": [
        {
          "egfrMin": 0.0,
          "egfrMax": 200.0,
          "adjustmentFactor": null,
          "maxDose": null,
          "maxDoseUnit": null,
          "frequency": null,
          "recommendation": "Can cause hyperkalemia (by 2-3 fold) and acute kidney injury (by 2-fold). Use with caution due to increased risk of adverse effects. Monitor potassium levels closely.",
          "contraindicated": false,
          "actionType": "MONITOR"
        }
      ],
      "hepaticAdjustments": null,
      "sourcePage": 50,
      "sourceSnippet": "Steroidal MRA, such as spironolactone and eplerenone, have established cardiovascular benefits in those with heart failure... However, their effects on kidney disease progression (eGFR decline or kidney failure) have not been examined in larger trials... the use of steroidal MRA also increases the risk of hyperkalemia (by 2\u20133 fold) and acute kidney injury (by 2-fold), and spironolactone can cause gynecomastia.",
      "guidelineVersion": "2022",
      "guidelineDoi": "10.1016/j.kint.2022.06.008",
      "recommendationId": "Key_information_2",
      "governance": {
        "sourceAuthority": "KDIGO",
        "sourceDocument": "KDIGO 2022 Diabetes in CKD",
        "sourceSection": "Key_information_2",
        "sourcePage": 50,
        "evidenceLevel": "",
        "effectiveDate": "2022-11-01",
        "guidelineDoi": "10.1016/j.kint.2022.06.008"
      }
    }
  ],
  "extractionDate": "2026-03-03",
  "extractorVersion": "v3.0.0-facts",
  "sourceGuideline": "KDIGO 2022 Diabetes in CKD",
  "totalDrugsExtracted": 1
}